wcpan/watchdog/__init__.py
wcpan/watchdog/__main__.py
wcpan/watchdog/filters.py
wcpan/watchdog/main.py
wcpan/watchdog/py.typed
wcpan/watchdog/walker.py
wcpan/watchdog/watcher.py
wcpan_watchdog-1.3.1.dist-info/LICENSE.txt
wcpan_watchdog-1.3.1.dist-info/METADATA
wcpan_watchdog-1.3.1.dist-info/WHEEL
wcpan_watchdog-1.3.1.dist-info/entry_points.txt
wcpan_watchdog-1.3.1.dist-info/RECORD
